MANIFEST.in
NEWS.txt
README.rst
setup.py
cloudy_release_client.egg-info/PKG-INFO
cloudy_release_client.egg-info/SOURCES.txt
cloudy_release_client.egg-info/dependency_links.txt
cloudy_release_client.egg-info/entry_points.txt
cloudy_release_client.egg-info/not-zip-safe
cloudy_release_client.egg-info/pbr.json
cloudy_release_client.egg-info/requires.txt
cloudy_release_client.egg-info/top_level.txt
cloudyclient/__init__.py
cloudyclient/checkout.py
cloudyclient/client.py
cloudyclient/conf.py
cloudyclient/deploy.py
cloudyclient/exceptions.py
cloudyclient/log.py
cloudyclient/state.py
cloudyclient/api/__init__.py
cloudyclient/api/base.py
cloudyclient/api/script.py
cloudyclient/api/shell.py
cloudyclient/api/virtualenv.py
cloudyclient/cli/__init__.py
cloudyclient/cli/base.py
cloudyclient/cli/deploy.py
cloudyclient/cli/poll.py
cloudyclient/tests/__init__.py
cloudyclient/tests/test_api.py
cloudyclient/tests/test_conf.py
cloudyclient/tests/test_deploy.py
cloudyclient/tests/utils/__init__.py
cloudyclient/utils/__init__.py