Metadata-Version: 1.0
Name: cloudy-release-client
Version: 0.10.0
Summary: Client program and library for cloudy-release.
Home-page: https://github.com/flupke/cloudy-release-client
Author: Luper Rouch
Author-email: luper.rouch@gmail.com
License: MIT
Keywords: deployment cloudy-release
Platform: UNKNOWN
